tiktoken/core.py
tiktoken/registry.py
tiktoken/__init__.py
tiktoken/_tiktoken.cpython-311-aarch64-linux-musl.so
tiktoken/py.typed
tiktoken/load.py
tiktoken/model.py
pandora_tiktoken.libs/libgcc_s-4e37474d.so.1
pandora_tiktoken-0.3.1.dist-info/top_level.txt
pandora_tiktoken-0.3.1.dist-info/LICENSE
pandora_tiktoken-0.3.1.dist-info/RECORD
pandora_tiktoken-0.3.1.dist-info/WHEEL
pandora_tiktoken-0.3.1.dist-info/METADATA
tiktoken_ext/openai_public.py
