Metadata-Version: 2.1
Name: pandora-tiktoken
Version: 0.3.1
Summary: tiktoken is a fast BPE tokeniser for use with OpenAI's models
Author: Shantanu Jain, Neo Peng
Author-email: shantanu@openai.com, pengzhile@gmail.com
License: MIT License
Project-URL: homepage, https://zhile.io
Project-URL: repository, https://github.com/pengzhile/pandora
Requires-Python: >=3.7
License-File: LICENSE
Requires-Dist: blobfile (>=2)
Requires-Dist: regex (>=2022.1.18)
Requires-Dist: requests (>=2.26.0)
Requires-Dist: typing-extensions (>=4.5.0)
